build/lib/dydactic/__init__.py
build/lib/dydactic/cast.py
build/lib/dydactic/options.py
build/lib/dydactic/record.py
build/lib/dydactic/result.py
build/lib/dydactic/validate.py
build/lib/tests/test_dicts.py
dydactic/__init__.py
dydactic/cast.py
dydactic/options.py
dydactic/record.py
dydactic/result.py
dydactic/validate.py
tests/test_dicts.py
dydactic-0.1.2.dist-info/METADATA
dydactic-0.1.2.dist-info/WHEEL
dydactic-0.1.2.dist-info/top_level.txt
dydactic-0.1.2.dist-info/RECORD
