Metadata-Version: 2.1
Name: dydactic
Version: 0.1.2
Summary: Validate iterables using Pydantic
License: MIT License
Keywords: iterable,validation,iterator,model
Requires-Python: >=3.10
Requires-Dist: pydantic>=2.9.2
Requires-Dist: python-dateutil
